GatorHoldEm/AiInstallation.py
GatorHoldEm/CMakeLists.txt
GatorHoldEm/SocketIOClient.py
GatorHoldEm/SocketIOServer.py
GatorHoldEm/__init__.py
GatorHoldEm/ai.cpp
GatorHoldEm/ai.py
GatorHoldEm/card.py
GatorHoldEm/deck.py
GatorHoldEm/player.py
GatorHoldEm/room.py
GatorHoldEm/table.py
GatorHoldEm/res/10_of_clubs.png
GatorHoldEm/res/10_of_diamonds.png
GatorHoldEm/res/10_of_hearts.png
GatorHoldEm/res/10_of_spades.png
GatorHoldEm/res/2_of_clubs.png
GatorHoldEm/res/2_of_diamonds.png
GatorHoldEm/res/2_of_hearts.png
GatorHoldEm/res/2_of_spades.png
GatorHoldEm/res/3_of_clubs.png
GatorHoldEm/res/3_of_diamonds.png
GatorHoldEm/res/3_of_hearts.png
GatorHoldEm/res/3_of_spades.png
GatorHoldEm/res/4_of_clubs.png
GatorHoldEm/res/4_of_diamonds.png
GatorHoldEm/res/4_of_hearts.png
GatorHoldEm/res/4_of_spades.png
GatorHoldEm/res/5_of_clubs.png
GatorHoldEm/res/5_of_diamonds.png
GatorHoldEm/res/5_of_hearts.png
GatorHoldEm/res/5_of_spades.png
GatorHoldEm/res/6_of_clubs.png
GatorHoldEm/res/6_of_diamonds.png
GatorHoldEm/res/6_of_hearts.png
GatorHoldEm/res/6_of_spades.png
GatorHoldEm/res/7_of_clubs.png
GatorHoldEm/res/7_of_diamonds.png
GatorHoldEm/res/7_of_hearts.png
GatorHoldEm/res/7_of_spades.png
GatorHoldEm/res/8_of_clubs.png
GatorHoldEm/res/8_of_diamonds.png
GatorHoldEm/res/8_of_hearts.png
GatorHoldEm/res/8_of_spades.png
GatorHoldEm/res/9_of_clubs.png
GatorHoldEm/res/9_of_diamonds.png
GatorHoldEm/res/9_of_hearts.png
GatorHoldEm/res/9_of_spades.png
GatorHoldEm/res/Key.png
GatorHoldEm/res/Rankings.png
GatorHoldEm/res/ace_of_clubs.png
GatorHoldEm/res/ace_of_diamonds.png
GatorHoldEm/res/ace_of_hearts.png
GatorHoldEm/res/ace_of_spades.png
GatorHoldEm/res/back.png
GatorHoldEm/res/back@2x.png
GatorHoldEm/res/bb_token.png
GatorHoldEm/res/d_token.png
GatorHoldEm/res/felt.png
GatorHoldEm/res/handranks.tar.gz
GatorHoldEm/res/jack_of_clubs.png
GatorHoldEm/res/jack_of_diamonds.png
GatorHoldEm/res/jack_of_hearts.png
GatorHoldEm/res/jack_of_spades.png
GatorHoldEm/res/king_of_clubs.png
GatorHoldEm-2.1.dist-info/LICENSE.txt
GatorHoldEm-2.1.dist-info/METADATA
GatorHoldEm-2.1.dist-info/WHEEL
GatorHoldEm-2.1.dist-info/entry_points.txt
GatorHoldEm-2.1.dist-info/top_level.txt
GatorHoldEm-2.1.dist-info/RECORD
